README.rst
setup.py
rings/__init__.py
rings/fitt.py
rings/ring.py
rings/utils.py
rings.egg-info/PKG-INFO
rings.egg-info/SOURCES.txt
rings.egg-info/dependency_links.txt
rings.egg-info/requires.txt
rings.egg-info/top_level.txt
rings.egg-info/zip-safe
rings/misc/montecarlo.py