Metadata-Version: 1.1
Name: rings
Version: 0.7.3
Summary: Procedures to handle coherent vortexes in the ocean
Home-page: http://cheeseshop.python.org/pypi/rings
Author: Guilherme Castelao, Luiz Irber
Author-email: guilherme@castelao.net, luiz.irber@gmail.com
License: PSF
Download-URL: http://cheeseshop.python.org/packages/source/P/rings/rings-0.7.3.tar.gz
Keywords: rings,eddies,ADCP,Gradient Balance
Platform: any
Classifier: Development Status :: 4 - Beta
Classifier: Environment :: Console
Classifier: Intended Audience :: Science/Research
Classifier: Intended Audience :: Developers
Classifier: License :: OSI Approved :: Python Software Foundation License
Classifier: Operating System :: OS Independent
Classifier: Programming Language :: Python
Classifier: Topic :: Scientific/Engineering
Classifier: Topic :: Software Development :: Libraries :: Python Modules
